<?xml version="1.0"?>
<page xmlns:xsi="http://www.w3.org/2001/XMLSchema-instance" xsi:noNamespaceSchemaLocation="urn:magento:framework:View/Layout/etc/page_configuration.xsd">
    <head>
        <css src="CopeX_FilterGrouping::css/groupedFilter.css" type="text/css" />
    </head>
    <body>
        <referenceBlock name="catalog.navigation.renderer">
               <block class="CopeX\FilterGrouping\Block\Navigation\Renderer\Group"
                      name="catalog.navigation.renderer.group" />
        </referenceBlock>
    </body>
</page>
